{
  "$schema": "https://ui.shadcn.com/schema/registry-item.json",
  "name": "bookmark-plus",
  "type": "registry:ui",
  "registryDependencies": [],
  "dependencies": [
    "motion"
  ],
  "devDependencies": [],
  "files": [
    {
      "path": "bookmark-plus.tsx",
      "content": "'use client';\r\n\r\nimport type { Variants } from 'motion/react';\r\nimport type { HTMLAttributes } from 'react';\r\nimport { forwardRef, useCallback, useImperativeHandle, useRef } from 'react';\r\nimport { motion, useAnimation } from 'motion/react';\r\n\r\nimport { cn } from '@/lib/utils';\r\n\r\nexport interface BookmarkPlusIconHandle {\r\n  startAnimation: () => void;\r\n  stopAnimation: () => void;\r\n}\r\n\r\ninterface BookmarkPlusIconProps extends HTMLAttributes<HTMLDivElement> {\r\n  size?: number;\r\n}\r\n\r\nconst BOOKMARK_VARIANTS: Variants = {\r\n  normal: { scaleY: 1, scaleX: 1 },\r\n  animate: {\r\n    scaleY: [1, 1.3, 0.9, 1.05, 1],\r\n    scaleX: [1, 0.9, 1.1, 0.95, 1],\r\n    transition: {\r\n      duration: 0.6,\r\n      ease: 'easeOut',\r\n    },\r\n  },\r\n};\r\n\r\nconst PLUS_LINE_VARIANTS: Variants = {\r\n  normal: { strokeDashoffset: 0, opacity: 1 },\r\n  animate: (i: number) => ({\r\n    strokeDashoffset: [1, 0],\r\n    opacity: 1,\r\n    transition: {\r\n      duration: 0.3,\r\n      ease: 'easeOut',\r\n      delay: i * 0.1,\r\n    },\r\n  }),\r\n};\r\n\r\nconst BookmarkPlusIcon = forwardRef<\r\n  BookmarkPlusIconHandle,\r\n  BookmarkPlusIconProps\r\n>(({ className, size = 28, onMouseEnter, onMouseLeave, ...props }, ref) => {\r\n  const controls = useAnimation();\r\n  const isControlledRef = useRef(false);\r\n\r\n  useImperativeHandle(ref, () => {\r\n    isControlledRef.current = true;\r\n    return {\r\n      startAnimation: () => controls.start('animate'),\r\n      stopAnimation: () => controls.start('normal'),\r\n    };\r\n  });\r\n\r\n  const handleMouseEnter = useCallback(\r\n    (e: React.MouseEvent<HTMLDivElement>) => {\r\n      if (!isControlledRef.current) {\r\n        controls.start('animate');\r\n      } else {\r\n        onMouseEnter?.(e);\r\n      }\r\n    },\r\n    [controls, onMouseEnter]\r\n  );\r\n\r\n  const handleMouseLeave = useCallback(\r\n    (e: React.MouseEvent<HTMLDivElement>) => {\r\n      if (!isControlledRef.current) {\r\n        controls.start('normal');\r\n      } else {\r\n        onMouseLeave?.(e);\r\n      }\r\n    },\r\n    [controls, onMouseLeave]\r\n  );\r\n\r\n  return (\r\n    <div\r\n      className={cn(className)}\r\n      onMouseEnter={handleMouseEnter}\r\n      onMouseLeave={handleMouseLeave}\r\n      {...props}\r\n    >\r\n      <svg\r\n        xmlns=\"http://www.w3.org/2000/svg\"\r\n        width={size}\r\n        height={size}\r\n        viewBox=\"0 0 24 24\"\r\n        fill=\"none\"\r\n        stroke=\"currentColor\"\r\n        strokeWidth=\"2\"\r\n        strokeLinecap=\"round\"\r\n        strokeLinejoin=\"round\"\r\n      >\r\n        <motion.path\r\n          d=\"m19 21-7-4-7 4V5a2 2 0 0 1 2-2h10a2 2 0 0 1 2 2v16z\"\r\n          animate={controls}\r\n          variants={BOOKMARK_VARIANTS}\r\n          style={{ originX: 0.5, originY: 0.5 }}\r\n        />\r\n\r\n        <motion.line\r\n          x1=\"12\"\r\n          x2=\"12\"\r\n          y1=\"7\"\r\n          y2=\"13\"\r\n          animate={controls}\r\n          variants={PLUS_LINE_VARIANTS}\r\n          custom={0}\r\n          initial=\"normal\"\r\n          strokeDasharray=\"1 1\"\r\n          pathLength=\"1\"\r\n        />\r\n        <motion.line\r\n          x1=\"15\"\r\n          x2=\"9\"\r\n          y1=\"10\"\r\n          y2=\"10\"\r\n          animate={controls}\r\n          variants={PLUS_LINE_VARIANTS}\r\n          custom={1}\r\n          initial=\"normal\"\r\n          strokeDasharray=\"1 1\"\r\n          pathLength=\"1\"\r\n        />\r\n      </svg>\r\n    </div>\r\n  );\r\n});\r\n\r\nBookmarkPlusIcon.displayName = 'BookmarkPlusIcon';\r\n\r\nexport { BookmarkPlusIcon };\r\n",
      "type": "registry:ui"
    }
  ]
}